README.rst
setup.py
coconet/__init__.py
coconet/clustering.py
coconet/coconet.py
coconet/dl.py
coconet/fragmentation.py
coconet/log.py
coconet/parser.py
coconet/util.py
coconet/core/__init__.py
coconet/core/composition_feature.py
coconet/core/config.py
coconet/core/coverage_feature.py
coconet/core/feature.py
coconet/core/generators.py
coconet/core/torch_models.py
coconet_binning.egg-info/PKG-INFO
coconet_binning.egg-info/SOURCES.txt
coconet_binning.egg-info/dependency_links.txt
coconet_binning.egg-info/entry_points.txt
coconet_binning.egg-info/not-zip-safe
coconet_binning.egg-info/requires.txt
coconet_binning.egg-info/top_level.txt
tests/__init__.py
tests/data.py
tests/test_clustering.py
tests/test_coconet.py
tests/test_config.py
tests/test_dl.py
tests/test_fragmentation.py
tests/test_generators.py
tests/test_preprocessing.py