Metadata-Version: 2.1
Name: coconet-binning
Version: 0.11.0
Summary: A contig binning tool from viral metagenomes
Home-page: https://github.com/Puumanamana/CoCoNet
Author: Cedric Arisdakessian
Author-email: carisdak@hawaii.edu
License: Apache License 2.0
Keywords: binning metagenomics deep learning virus clustering
Platform: UNKNOWN
Requires-Python: >=3.6
